{
  "dslNameList": [
    "DefaultDSL",
    "HierarchyDSL",
    "TextLabelsDSL",
    "DialogDSL"
  ],
  "view": {
    "scale": 0.6299831555306008,
    "position": [
      -1225,
      -1358.575293873047
    ],
    "isGridOn": false
  },
  "model": "{ \"class\": \"GraphLinksModel\",\n  \"copiesArrays\": true,\n  \"copiesArrayObjects\": true,\n  \"copiesKey\": false,\n  \"linkKeyProperty\": \"key\",\n  \"linkFromPortIdProperty\": \"fromPort\",\n  \"linkToPortIdProperty\": \"toPort\",\n  \"nodeDataArray\": [ \n{\"label\":\"Initialize Receptionist\", \"tag\":\"\", \"type\":\"\", \"category\":\"Dialog_Component\", \"size\":\"125 100\", \"in\":[], \"out\":[ {\"portId\":\"check_WhatToDo\"} ], \"isDir\":true, \"key\":2, \"location\":\"620 -580\", \"fileURL\":\"/fileServer/00/08.json\", \"fileType\":\"text/json\"},\n{\"label\":\"Analyse user state\", \"tag\":\"\", \"type\":\"\", \"category\":\"Dialog_Component\", \"size\":\"125 180\", \"in\":[], \"out\":[ {\"portId\":\"isUserInFrontOfMe\"},{\"portId\":\"isUserLookingAtMe\"},{\"portId\":\"isUserRecognized\"},{\"portId\":\"isUserSpeaking\"},{\"portId\":\"isUserPresentedWithKeyboard\"},{\"portId\":\"hasUserFinishedTyping\"},{\"portId\":\"isUserPresentedWithButtons\"},{\"portId\":\"hasUserClickedAButton\"} ], \"isDir\":true, \"key\":3, \"location\":\"-1180 -220\", \"fileURL\":\"/fileServer/00/00.json\", \"fileType\":\"text/json\"},\n{\"label\":\"Analyse user reaction\", \"tag\":\"\", \"type\":\"\", \"category\":\"Dialog_Component\", \"size\":\"125 125\", \"in\":[ {\"portId\":\"isUserSpeaking\"},{\"portId\":\"hasUserFinishedTyping\"},{\"portId\":\"wait_ForAnswer\"} ], \"out\":[ {\"portId\":\"isAnswerUnderstood\"},{\"portId\":\"isUserSilent\"},{\"portId\":\"isNoUserReaction\"} ], \"isDir\":true, \"key\":6, \"location\":\"-600 289.90000000000003\", \"fileURL\":\"/fileServer/00/04.json\", \"fileType\":\"text/json\"},\n{\"label\":\"Analyse understood user answer\", \"tag\":\"\", \"type\":\"\", \"category\":\"Dialog_Component\", \"size\":\"125 260\", \"in\":[ {\"portId\":\"isAnswerUnderstood\"} ], \"out\":[ {\"portId\":\"isSayingHello\"},{\"portId\":\"isSayingHeHasAMeeting \"},{\"portId\":\"isGivingHisName\"},{\"portId\":\"isGivingHisCompanyName\"},{\"portId\":\"isGivingHisContactName\"},{\"portId\":\"isConfirmingHisName\"},{\"portId\":\"isDenyingHisName\"},{\"portId\":\"isRequestingToRepeat\"},{\"portId\":\"isAskingToCallHisContact\"},{\"portId\":\"isSayingHisContactNotComing\"},{\"portId\":\"isAcceptingGDPRConsent\"},{\"portId\":\"isRefusingGDPRConsent\"} ], \"isDir\":true, \"key\":-15, \"location\":\"-50 -40.39999999999998\", \"fileURL\":\"/fileServer/00/05.json\", \"fileType\":\"text/json\"},\n{\"label\":\"Analyse what to do\", \"tag\":\"\", \"type\":\"\", \"category\":\"Dialog_Component\", \"size\":\"125 730\", \"in\":[ {\"portId\":\"check_WhatToDo\"},{\"portId\":\"speech_Done\"},{\"portId\":\"emotion_Done\"},{\"portId\":\"move_Done\"},{\"portId\":\"gaze_Done\"},{\"portId\":\"eyes_Done\"},{\"portId\":\"ears_Done\"},{\"portId\":\"rightHand_Done\"},{\"portId\":\"leftHand_Done\"},{\"portId\":\"in\"},{\"portId\":\"isUserFound\"},{\"portId\":\"isUserFoundUniquely\"},{\"portId\":\"isUserInFrontOfMe\"},{\"portId\":\"isUserLookingAtMe\"},{\"portId\":\"isUserRecognized\"},{\"portId\":\"isUserSpeaking\"},{\"portId\":\"isUserTyping\"},{\"portId\":\"isSayingHello\"},{\"portId\":\"isSayingHeHasAMeeting \"},{\"portId\":\"isGivingHisName\"},{\"portId\":\"isGivingHisCompanyName\"},{\"portId\":\"isGivingHisContactName\"},{\"portId\":\"isConfirmingHisName\"},{\"portId\":\"isDenyingHisName\"},{\"portId\":\"isRequestingToRepeat\"},{\"portId\":\"isAskingToCallHisContact\"},{\"portId\":\"isSayingHisContactNotComing\"},{\"portId\":\"isAcceptingGDPRConsent\"},{\"portId\":\"isRefusingGDPRConsent\"},{\"portId\":\"isSpeakingAboutHisName\"},{\"portId\":\"isSpeakingAboutHisCompanyName\"},{\"portId\":\"isSpeakingAboutHisContactName\"},{\"portId\":\"isAnswerUnderstood\"},{\"portId\":\"isUserSilent\"},{\"portId\":\"isNoUserReaction\"},{\"portId\":\"isCallSuccessfull\"},{\"portId\":\"isNoAnswer\"} ], \"out\":[ {\"portId\":\"ask_Something\"},{\"portId\":\"say_Something\"},{\"portId\":\"express_Emotion_\"},{\"portId\":\"move_Somewhere\"},{\"portId\":\"gaze_somewhere\"},{\"portId\":\"do_WithEyes\"},{\"portId\":\"do_WithEars\"},{\"portId\":\"do_withRightHand\"},{\"portId\":\"do_WithLeftHand\"},{\"portId\":\"do_InMemory\"} ], \"isDir\":true, \"key\":18, \"location\":\"1340 -70.20000000000005\", \"fileURL\":\"/fileServer/00/09.json\", \"fileType\":\"text/json\"},\n{\"label\":\"Analyse partially understood user answer\", \"tag\":\"\", \"type\":\"\", \"category\":\"Dialog_Component\", \"size\":\"125 100\", \"in\":[ {\"portId\":\"isAnswerUnderstood\"} ], \"out\":[ {\"portId\":\"isSpeakingAboutHisName\"},{\"portId\":\"isSpeakingAboutHisCompanyName\"},{\"portId\":\"isSpeakingAboutHisContactName\"} ], \"isDir\":true, \"key\":20, \"location\":\"-50 159.70000000000002\", \"fileURL\":\"/fileServer/00/06.json\", \"fileType\":\"text/json\"},\n{\"label\":\"I recall something from memory\", \"tag\":\"\", \"type\":\"\", \"category\":\"Dialog_Component\", \"size\":\"125 100\", \"in\":[ {\"portId\":\"isUserRecognized\"},{\"portId\":\"isGivingHisName\"},{\"portId\":\"isGivingHisCompanyName\"},{\"portId\":\"isGivingHisContactName\"} ], \"out\":[ {\"portId\":\"isUserFound\"},{\"portId\":\"isUserFoundUniquely\"} ], \"isDir\":true, \"key\":28, \"location\":\"600 -310\", \"fileURL\":\"/fileServer/00/07.json\", \"fileType\":\"text/json\"},\n{\"label\":\"Do something\", \"tag\":\"\", \"type\":\"\", \"category\":\"Dialog_Component\", \"size\":\"125 215\", \"in\":[ {\"portId\":\"ask_Something\"},{\"portId\":\"say_Something\"},{\"portId\":\"express_Emotion_\"},{\"portId\":\"move_Somewhere\"},{\"portId\":\"gaze_Somewhere\"},{\"portId\":\"do_WithEyes\"},{\"portId\":\"do_WithEars\"},{\"portId\":\"do_WithRightHand\"},{\"portId\":\"do_WithLeftHand\"},{\"portId\":\"do_InMemory\"} ], \"out\":[ {\"portId\":\"wait_ForAnswer\"},{\"portId\":\"speech_Done\"},{\"portId\":\"emotion_Done\"},{\"portId\":\"move_Done\"},{\"portId\":\"gaze_Done\"},{\"portId\":\"eyes_Done\"},{\"portId\":\"ears_Done\"},{\"portId\":\"rightHand_Done\"},{\"portId\":\"leftHand_Done\"},{\"portId\":\"memory_Done\"} ], \"isDir\":true, \"key\":47, \"location\":\"1900 -90.79999999999995\", \"fileURL\":\"/fileServer/00/10.json\", \"fileType\":\"text/json\"},\n{\"label\":\"Analyse phone call state\", \"tag\":\"\", \"type\":\"\", \"category\":\"Dialog_Component\", \"size\":\"125 100\", \"in\":[], \"out\":[ {\"portId\":\"isCallSuccessfull\"},{\"portId\":\"isNoAnswer\"} ], \"isDir\":true, \"key\":48, \"location\":\"620 360\", \"fileURL\":\"\", \"fileType\":\"text/json\"},\n{\"label\":\"Perception\", \"category\":\"TextLabels_Size4\", \"size\":\"495 30\", \"key\":24, \"location\":\"-40 380\"},\n{\"label\":\"Actions\", \"category\":\"TextLabels_Size4\", \"size\":\"495 30\", \"key\":25, \"location\":\"1730 100\"},\n{\"label\":\"Decisions\", \"category\":\"TextLabels_Size4\", \"size\":\"495 30\", \"key\":22, \"location\":\"1060 370\"},\n{\"label\":\"Avatar Receptionist\", \"category\":\"TextLabels_Size5\", \"size\":\"1415 30\", \"key\":29, \"location\":\"-150 -800\"},\n{\"label\":\"Model\", \"size\":\"180 60\", \"category\":\"Hierarchy_Model\", \"isFile\":true, \"fileType\":\"text/json\", \"isSystem\":\"$GraphModel$\", \"key\":14, \"location\":\"-460 -780\", \"editorPosition\":[ 1762,538,528,1109 ]},\n{\"label\":\"Selection\", \"size\":\"180 60\", \"category\":\"Hierarchy_Selection\", \"isFile\":true, \"fileType\":\"text/json\", \"isSystem\":\"$GraphSelection$\", \"key\":16, \"location\":\"-770 -780\", \"editorPosition\":[ 1272,1067,461,670 ]},\n{\"label\":\"DialogDSL\", \"size\":\"180 35\", \"category\":\"Hierarchy_DataInFile\", \"isFile\":true, \"fileType\":\"text/javascript\", \"fileURL\":\"/fileServer/DialogDSL.js\", \"key\":19, \"location\":\"-1020 -810\", \"editorPosition\":[ 2148,433,880,1319 ]},\n{\"label\":\"DialogDSL\", \"size\":\"180 60\", \"category\":\"Hierarchy_DSL\", \"isFile\":true, \"fileType\":\"text/javascript\", \"isSystem\":\"$GraphDSL$\", \"fileURL\":\"\", \"key\":23, \"location\":\"-1220 -940.1\"}\n ],\n  \"linkDataArray\": [ \n{\"category\":\"Dialog_Component\", \"fromPort\":\"wait_ForAnswer\", \"toPort\":\"wait_ForAnswer\", \"from\":47, \"to\":6, \"points\":[2147.9580078125,-180.79999999999995,2157.9580078125,-180.79999999999995,2215,-180,2215,-490,-1215,-490,-1215,290,-777.302734375,309.90000000000003,-767.302734375,309.90000000000003], \"key\":-17},\n{\"category\":\"Dialog_Component\", \"fromPort\":\"ask_Something\", \"toPort\":\"ask_Something\", \"from\":18, \"to\":47, \"points\":[1602.7236328125,-160.20000000000005,1612.7236328125,-160.20000000000005,1751.490234375,-180.79999999999995,1761.490234375,-180.79999999999995], \"key\":-53},\n{\"category\":\"Dialog_Component\", \"fromPort\":\"isUserFound\", \"toPort\":\"isUserFound\", \"from\":28, \"to\":18, \"points\":[879.8408203125,-320,889.8408203125,-320,975,-230,1086.4423828125,-230.20000000000005,1096.4423828125,-230.20000000000005], \"key\":-51},\n{\"category\":\"Dialog_Component\", \"fromPort\":\"isUserFoundUniquely\", \"toPort\":\"isUserFoundUniquely\", \"from\":28, \"to\":18, \"points\":[879.8408203125,-300,889.8408203125,-300,970,-210,1086.4423828125,-210.20000000000005,1096.4423828125,-210.20000000000005], \"key\":-59},\n{\"category\":\"Dialog_Component\", \"fromPort\":\"isUserInFrontOfMe\", \"toPort\":\"isUserInFrontOfMe\", \"from\":3, \"to\":18, \"points\":[-842.580078125,-290,-832.580078125,-290,1086.4423828125,-190.20000000000005,1096.4423828125,-190.20000000000005], \"key\":-74},\n{\"category\":\"Dialog_Component\", \"fromPort\":\"isUserLookingAtMe\", \"toPort\":\"isUserLookingAtMe\", \"from\":3, \"to\":18, \"points\":[-842.580078125,-270,-832.580078125,-270,1086.4423828125,-170.20000000000005,1096.4423828125,-170.20000000000005], \"key\":-81},\n{\"category\":\"Dialog_Component\", \"fromPort\":\"isUserRecognized\", \"toPort\":\"isUserRecognized\", \"from\":3, \"to\":18, \"points\":[-842.580078125,-250,-832.580078125,-250,1086.4423828125,-150.20000000000005,1096.4423828125,-150.20000000000005], \"key\":-90},\n{\"category\":\"Dialog_Component\", \"fromPort\":\"isSpeakingAboutHisName\", \"toPort\":\"isSpeakingAboutHisName\", \"from\":20, \"to\":18, \"points\":[318.5576171875,139.70000000000002,328.5576171875,139.70000000000002,1086.4423828125,149.79999999999995,1096.4423828125,149.79999999999995], \"key\":-101},\n{\"category\":\"Dialog_Component\", \"fromPort\":\"isSpeakingAboutHisCompanyName\", \"toPort\":\"isSpeakingAboutHisCompanyName\", \"from\":20, \"to\":18, \"points\":[318.5576171875,159.70000000000002,328.5576171875,159.70000000000002,1086.4423828125,169.79999999999995,1096.4423828125,169.79999999999995], \"key\":-102},\n{\"category\":\"Dialog_Component\", \"fromPort\":\"isSpeakingAboutHisContactName\", \"toPort\":\"isSpeakingAboutHisContactName\", \"from\":20, \"to\":18, \"points\":[318.5576171875,179.70000000000002,328.5576171875,179.70000000000002,1086.4423828125,189.79999999999995,1096.4423828125,189.79999999999995], \"key\":-103},\n{\"category\":\"Dialog_Component\", \"fromPort\":\"isCallSuccessfull\", \"toPort\":\"isCallSuccessfull\", \"from\":48, \"to\":18, \"points\":[871.0341796875,350,881.0341796875,350,1086.4423828125,269.79999999999995,1096.4423828125,269.79999999999995], \"key\":-104},\n{\"category\":\"Dialog_Component\", \"fromPort\":\"isNoAnswer\", \"toPort\":\"isNoAnswer\", \"from\":48, \"to\":18, \"points\":[871.0341796875,370,881.0341796875,370,1086.4423828125,289.79999999999995,1096.4423828125,289.79999999999995], \"key\":-105},\n{\"category\":\"Dialog_Component\", \"fromPort\":\"isUserSilent\", \"toPort\":\"isUserSilent\", \"from\":6, \"to\":18, \"points\":[-324.828125,289.90000000000003,-314.828125,289.90000000000003,1086.4423828125,229.79999999999995,1096.4423828125,229.79999999999995], \"key\":-107},\n{\"category\":\"Dialog_Component\", \"fromPort\":\"isNoUserReaction\", \"toPort\":\"isNoUserReaction\", \"from\":6, \"to\":18, \"points\":[-324.828125,309.90000000000003,-314.828125,309.90000000000003,1086.4423828125,249.79999999999995,1096.4423828125,249.79999999999995], \"key\":-108},\n{\"category\":\"Dialog_Component\", \"fromPort\":\"say_Something\", \"toPort\":\"say_Something\", \"from\":18, \"to\":47, \"points\":[1602.7236328125,-140.20000000000005,1612.7236328125,-140.20000000000005,1751.490234375,-160.79999999999995,1761.490234375,-160.79999999999995], \"key\":-55},\n{\"category\":\"Dialog_Component\", \"fromPort\":\"move_Somewhere\", \"toPort\":\"move_Somewhere\", \"from\":18, \"to\":47, \"points\":[1602.7236328125,-100.20000000000005,1612.7236328125,-100.20000000000005,1751.490234375,-120.79999999999995,1761.490234375,-120.79999999999995], \"key\":-54},\n{\"category\":\"Dialog_Component\", \"fromPort\":\"gaze_somewhere\", \"toPort\":\"gaze_Somewhere\", \"from\":18, \"to\":47, \"points\":[1602.7236328125,-80.20000000000005,1612.7236328125,-80.20000000000005,1751.490234375,-100.79999999999995,1761.490234375,-100.79999999999995], \"key\":-52},\n{\"category\":\"Dialog_Component\", \"fromPort\":\"isUserSpeaking\", \"toPort\":\"isUserSpeaking\", \"from\":3, \"to\":6, \"points\":[-842.580078125,-230,-832.580078125,-230,-777.302734375,269.90000000000003,-767.302734375,269.90000000000003], \"key\":-66},\n{\"category\":\"Dialog_Component\", \"fromPort\":\"hasUserFinishedTyping\", \"toPort\":\"hasUserFinishedTyping\", \"from\":3, \"to\":6, \"points\":[-842.580078125,-190,-832.580078125,-190,-777.302734375,289.90000000000003,-767.302734375,289.90000000000003], \"key\":-68},\n{\"category\":\"Dialog_Component\", \"fromPort\":\"isAnswerUnderstood\", \"toPort\":\"isAnswerUnderstood\", \"from\":6, \"to\":20, \"points\":[-324.828125,269.90000000000003,-314.828125,269.90000000000003,-210.171875,159.70000000000002,-200.171875,159.70000000000002], \"key\":-69},\n{\"category\":\"Dialog_Component\", \"fromPort\":\"isAnswerUnderstood\", \"toPort\":\"isAnswerUnderstood\", \"from\":6, \"to\":18, \"points\":[-324.828125,269.90000000000003,-314.828125,269.90000000000003,1086.4423828125,209.79999999999995,1096.4423828125,209.79999999999995], \"key\":-72},\n{\"category\":\"Dialog_Component\", \"fromPort\":\"isUserSpeaking\", \"toPort\":\"isUserSpeaking\", \"from\":3, \"to\":18, \"points\":[-842.580078125,-230,-832.580078125,-230,1086.4423828125,-130.20000000000005,1096.4423828125,-130.20000000000005], \"key\":-60},\n{\"category\":\"Dialog_Component\", \"fromPort\":\"express_Emotion_\", \"toPort\":\"express_Emotion_\", \"from\":18, \"to\":47, \"points\":[1602.7236328125,-120.20000000000005,1612.7236328125,-120.20000000000005,1751.490234375,-140.79999999999995,1761.490234375,-140.79999999999995], \"key\":-63},\n{\"category\":\"Dialog_Component\", \"fromPort\":\"speech_Done\", \"toPort\":\"speech_Done\", \"from\":47, \"to\":18, \"points\":[2147.9580078125,-160.79999999999995,2157.9580078125,-160.79999999999995,2250,-160,2250,-575,1060,-575,1060,-410,1086.4423828125,-410.20000000000005,1096.4423828125,-410.20000000000005], \"key\":-76},\n{\"category\":\"Dialog_Component\", \"fromPort\":\"check_WhatToDo\", \"toPort\":\"check_WhatToDo\", \"from\":2, \"to\":18, \"points\":[875.716796875,-580,885.716796875,-580,920,-430,1086.4423828125,-430.20000000000005,1096.4423828125,-430.20000000000005], \"key\":-62},\n{\"category\":\"Dialog_Component\", \"fromPort\":\"isUserRecognized\", \"toPort\":\"isUserRecognized\", \"from\":3, \"to\":28, \"points\":[-842.580078125,-250,-832.580078125,-250,335,-220,401.724609375,-340,411.724609375,-340], \"key\":-75},\n{\"category\":\"Dialog_Component\", \"fromPort\":\"do_withRightHand\", \"toPort\":\"do_WithRightHand\", \"from\":18, \"to\":47, \"points\":[1602.7236328125,-20.200000000000045,1612.7236328125,-20.200000000000045,1751.490234375,-40.799999999999955,1761.490234375,-40.799999999999955], \"key\":-58},\n{\"category\":\"Dialog_Component\", \"fromPort\":\"do_WithLeftHand\", \"toPort\":\"do_WithLeftHand\", \"from\":18, \"to\":47, \"points\":[1602.7236328125,-0.20000000000004547,1612.7236328125,-0.20000000000004547,1751.490234375,-20.799999999999955,1761.490234375,-20.799999999999955], \"key\":-65},\n{\"category\":\"Dialog_Component\", \"fromPort\":\"do_InMemory\", \"toPort\":\"do_InMemory\", \"from\":18, \"to\":47, \"points\":[1602.7236328125,19.799999999999955,1612.7236328125,19.799999999999955,1751.490234375,-0.7999999999999545,1761.490234375,-0.7999999999999545], \"key\":-67},\n{\"category\":\"Dialog_Component\", \"fromPort\":\"do_WithEyes\", \"toPort\":\"do_WithEyes\", \"from\":18, \"to\":47, \"points\":[1602.7236328125,-60.200000000000045,1612.7236328125,-60.200000000000045,1751.490234375,-80.79999999999995,1761.490234375,-80.79999999999995], \"key\":-56},\n{\"category\":\"Dialog_Component\", \"fromPort\":\"do_WithEars\", \"toPort\":\"do_WithEars\", \"from\":18, \"to\":47, \"points\":[1602.7236328125,-40.200000000000045,1612.7236328125,-40.200000000000045,1751.490234375,-60.799999999999955,1761.490234375,-60.799999999999955], \"key\":-57},\n{\"category\":\"Dialog_Component\", \"fromPort\":\"emotion_Done\", \"toPort\":\"emotion_Done\", \"from\":47, \"to\":18, \"points\":[2147.9580078125,-140.79999999999995,2157.9580078125,-140.79999999999995,2260,-140,2260,-585,1050,-585,1050,-390,1086.4423828125,-390.20000000000005,1096.4423828125,-390.20000000000005], \"key\":-49},\n{\"category\":\"Dialog_Component\", \"fromPort\":\"move_Done\", \"toPort\":\"move_Done\", \"from\":47, \"to\":18, \"points\":[2147.9580078125,-120.79999999999995,2157.9580078125,-120.79999999999995,2270,-120,2270,-595,1040,-595,1040,-370,1086.4423828125,-370.20000000000005,1096.4423828125,-370.20000000000005], \"key\":-50},\n{\"category\":\"Dialog_Component\", \"fromPort\":\"gaze_Done\", \"toPort\":\"gaze_Done\", \"from\":47, \"to\":18, \"points\":[2147.9580078125,-100.79999999999995,2157.9580078125,-100.79999999999995,2280,-100,2280,-605,1030,-605,1030,-350,1086.4423828125,-350.20000000000005,1096.4423828125,-350.20000000000005], \"key\":-64},\n{\"category\":\"Dialog_Component\", \"fromPort\":\"eyes_Done\", \"toPort\":\"eyes_Done\", \"from\":47, \"to\":18, \"points\":[2147.9580078125,-80.79999999999995,2157.9580078125,-80.79999999999995,2290,-80,2290,-615,1020,-615,1020,-330,1086.4423828125,-330.20000000000005,1096.4423828125,-330.20000000000005], \"key\":-70},\n{\"category\":\"Dialog_Component\", \"fromPort\":\"ears_Done\", \"toPort\":\"ears_Done\", \"from\":47, \"to\":18, \"points\":[2147.9580078125,-60.799999999999955,2157.9580078125,-60.799999999999955,2300,-60,2300,-625,1010,-625,1010,-310,1086.4423828125,-310.20000000000005,1096.4423828125,-310.20000000000005], \"key\":-71},\n{\"category\":\"Dialog_Component\", \"fromPort\":\"rightHand_Done\", \"toPort\":\"rightHand_Done\", \"from\":47, \"to\":18, \"points\":[2147.9580078125,-40.799999999999955,2157.9580078125,-40.799999999999955,2310,-40,2310,-635,1000,-635,1000,-290,1086.4423828125,-290.20000000000005,1096.4423828125,-290.20000000000005], \"key\":-73},\n{\"category\":\"Dialog_Component\", \"fromPort\":\"leftHand_Done\", \"toPort\":\"leftHand_Done\", \"from\":47, \"to\":18, \"points\":[2147.9580078125,-20.799999999999955,2157.9580078125,-20.799999999999955,2320,-20,2320,-645,990,-645,990,-270,1086.4423828125,-270.20000000000005,1096.4423828125,-270.20000000000005], \"key\":-77},\n{\"category\":\"Dialog_Component\", \"fromPort\":\"memory_Done\", \"toPort\":\"in\", \"from\":47, \"to\":18, \"points\":[2147.9580078125,-0.7999999999999545,2157.9580078125,-0.7999999999999545,2330,0,2330,-655,980,-655,980,-250,1086.4423828125,-250.20000000000005,1096.4423828125,-250.20000000000005], \"key\":-78},\n{\"category\":\"Dialog_Component\", \"fromPort\":\"isAnswerUnderstood\", \"toPort\":\"isAnswerUnderstood\", \"from\":6, \"to\":-15, \"points\":[-324.828125,269.90000000000003,-314.828125,269.90000000000003,-210.171875,-40.39999999999998,-200.171875,-40.39999999999998], \"key\":-40},\n{\"category\":\"Dialog_Condition\", \"fromPort\":\"\", \"toPort\":\"\", \"from\":23, \"to\":19, \"points\":[-1092.9625034916346,-909.8273585213083,-969.8960668388804,-829.7726414786918], \"key\":-41},\n{\"category\":\"Dialog_Component\", \"fromPort\":\"isGivingHisName\", \"toPort\":\"isGivingHisName\", \"from\":-15, \"to\":28, \"points\":[287.4130859375,-110.39999999999998,297.4130859375,-110.39999999999998,401.724609375,-320,411.724609375,-320], \"key\":-42},\n{\"category\":\"Dialog_Component\", \"fromPort\":\"isGivingHisCompanyName\", \"toPort\":\"isGivingHisCompanyName\", \"from\":-15, \"to\":28, \"points\":[287.4130859375,-90.39999999999998,297.4130859375,-90.39999999999998,401.724609375,-300,411.724609375,-300], \"key\":-43},\n{\"category\":\"Dialog_Component\", \"fromPort\":\"isGivingHisContactName\", \"toPort\":\"isGivingHisContactName\", \"from\":-15, \"to\":28, \"points\":[287.4130859375,-70.39999999999998,297.4130859375,-70.39999999999998,401.724609375,-280,411.724609375,-280], \"key\":-44},\n{\"category\":\"Dialog_Component\", \"fromPort\":\"isGivingHisContactName\", \"toPort\":\"isGivingHisContactName\", \"from\":-15, \"to\":18, \"points\":[287.4130859375,-70.39999999999998,297.4130859375,-70.39999999999998,1086.4423828125,-10.200000000000045,1096.4423828125,-10.200000000000045], \"key\":-46},\n{\"category\":\"Dialog_Component\", \"fromPort\":\"isGivingHisCompanyName\", \"toPort\":\"isGivingHisCompanyName\", \"from\":-15, \"to\":18, \"points\":[287.4130859375,-90.39999999999998,297.4130859375,-90.39999999999998,1086.4423828125,-30.200000000000045,1096.4423828125,-30.200000000000045], \"key\":-47},\n{\"category\":\"Dialog_Component\", \"fromPort\":\"isGivingHisName\", \"toPort\":\"isGivingHisName\", \"from\":-15, \"to\":18, \"points\":[287.4130859375,-110.39999999999998,297.4130859375,-110.39999999999998,1086.4423828125,-50.200000000000045,1096.4423828125,-50.200000000000045], \"key\":-48},\n{\"category\":\"Dialog_Component\", \"fromPort\":\"isDenyingHisName\", \"toPort\":\"isDenyingHisName\", \"from\":-15, \"to\":18, \"points\":[287.4130859375,-30.399999999999977,297.4130859375,-30.399999999999977,1086.4423828125,29.799999999999955,1096.4423828125,29.799999999999955], \"key\":-61},\n{\"category\":\"Dialog_Component\", \"fromPort\":\"isRequestingToRepeat\", \"toPort\":\"isRequestingToRepeat\", \"from\":-15, \"to\":18, \"points\":[287.4130859375,-10.399999999999977,297.4130859375,-10.399999999999977,1086.4423828125,49.799999999999955,1096.4423828125,49.799999999999955], \"key\":-79},\n{\"category\":\"Dialog_Component\", \"fromPort\":\"isAskingToCallHisContact\", \"toPort\":\"isAskingToCallHisContact\", \"from\":-15, \"to\":18, \"points\":[287.4130859375,9.600000000000023,297.4130859375,9.600000000000023,1086.4423828125,69.79999999999995,1096.4423828125,69.79999999999995], \"key\":-80},\n{\"category\":\"Dialog_Component\", \"fromPort\":\"isSayingHisContactNotComing\", \"toPort\":\"isSayingHisContactNotComing\", \"from\":-15, \"to\":18, \"points\":[287.4130859375,29.600000000000023,297.4130859375,29.600000000000023,1086.4423828125,89.79999999999995,1096.4423828125,89.79999999999995], \"key\":-82},\n{\"category\":\"Dialog_Component\", \"fromPort\":\"isAcceptingGDPRConsent\", \"toPort\":\"isAcceptingGDPRConsent\", \"from\":-15, \"to\":18, \"points\":[287.4130859375,49.60000000000002,297.4130859375,49.60000000000002,1086.4423828125,109.79999999999995,1096.4423828125,109.79999999999995], \"key\":-83},\n{\"category\":\"Dialog_Component\", \"fromPort\":\"isRefusingGDPRConsent\", \"toPort\":\"isRefusingGDPRConsent\", \"from\":-15, \"to\":18, \"points\":[287.4130859375,69.60000000000002,297.4130859375,69.60000000000002,1086.4423828125,129.79999999999995,1096.4423828125,129.79999999999995], \"key\":-84},\n{\"category\":\"Dialog_Component\", \"fromPort\":\"isConfirmingHisName\", \"toPort\":\"isConfirmingHisName\", \"from\":-15, \"to\":18, \"points\":[287.4130859375,-50.39999999999998,297.4130859375,-50.39999999999998,1086.4423828125,9.799999999999955,1096.4423828125,9.799999999999955], \"key\":-85}\n ]}"
}